{
	"id": "d78d8fe9-8754-a0ff-700a-a4583491246c",
	"name": "ProjectDemo",
	"description": "",
	"order": [
		"78ee16d6-bb31-dda0-7b3b-8011f10ccc35",
		"ee50c51c-2b4a-3044-704d-82e3393ab3ed",
		"fb90d9cb-f71b-1d61-3797-f0e4d7d55677",
		"4ec4615e-f28a-d3b5-53d6-ca6ba6b63a4a",
		"74f77bcb-6df6-5d1e-b6bb-02c80b576957"
	],
	"folders": [],
	"folders_order": [],
	"timestamp": 1535587776086,
	"owner": "929097",
	"public": false,
	"requests": [
		{
			"id": "4ec4615e-f28a-d3b5-53d6-ca6ba6b63a4a",
			"headers": "Content-Type: application/json\n",
			"headerData": [
				{
					"key": "Content-Type",
					"value": "application/json",
					"description": "",
					"enabled": true
				}
			],
			"url": "localhost:8080/product",
			"queryParams": [],
			"pathVariables": {},
			"pathVariableData": [],
			"preRequestScript": null,
			"method": "PUT",
			"collectionId": "d78d8fe9-8754-a0ff-700a-a4583491246c",
			"data": [],
			"dataMode": "raw",
			"name": "UpdateProduct",
			"description": "",
			"descriptionFormat": "html",
			"time": 1535587829415,
			"version": 2,
			"responses": [],
			"tests": null,
			"currentHelper": "normal",
			"helperAttributes": {},
			"rawModeData": "{\n\t\"id\":\"4\",\n\t\"description\": \"Teste update\",\n\t\"amount\": \"10\",\n\t\"price\": \"10.50\",\n\t\"type\": \"Pacote\",\n\t\"provider\": 1\n}"
		},
		{
			"id": "74f77bcb-6df6-5d1e-b6bb-02c80b576957",
			"headers": "",
			"headerData": [],
			"url": "localhost:8080/product/2",
			"queryParams": [],
			"pathVariables": {},
			"pathVariableData": [],
			"preRequestScript": null,
			"method": "DELETE",
			"collectionId": "d78d8fe9-8754-a0ff-700a-a4583491246c",
			"data": null,
			"dataMode": "params",
			"name": "DeleteProduct",
			"description": "",
			"descriptionFormat": "html",
			"time": 1535587841136,
			"version": 2,
			"responses": [],
			"tests": null,
			"currentHelper": "normal",
			"helperAttributes": {}
		},
		{
			"id": "78ee16d6-bb31-dda0-7b3b-8011f10ccc35",
			"headers": "",
			"headerData": [],
			"url": "localhost:8080/product",
			"queryParams": [],
			"pathVariables": {},
			"pathVariableData": [],
			"preRequestScript": null,
			"method": "GET",
			"collectionId": "d78d8fe9-8754-a0ff-700a-a4583491246c",
			"data": null,
			"dataMode": "params",
			"name": "GetAll",
			"description": "",
			"descriptionFormat": "html",
			"time": 1535587794370,
			"version": 2,
			"responses": [],
			"tests": null,
			"currentHelper": "normal",
			"helperAttributes": {}
		},
		{
			"id": "ee50c51c-2b4a-3044-704d-82e3393ab3ed",
			"headers": "Content-Type: application/json\n",
			"headerData": [
				{
					"key": "Content-Type",
					"value": "application/json",
					"description": "",
					"enabled": true
				}
			],
			"url": "localhost:8080/product",
			"queryParams": [],
			"pathVariables": {},
			"pathVariableData": [],
			"preRequestScript": null,
			"method": "POST",
			"collectionId": "d78d8fe9-8754-a0ff-700a-a4583491246c",
			"data": [],
			"dataMode": "raw",
			"name": "CreateProduct",
			"description": "",
			"descriptionFormat": "html",
			"time": 1535587807887,
			"version": 2,
			"responses": [],
			"tests": null,
			"currentHelper": "normal",
			"helperAttributes": {},
			"rawModeData": "{\n\t\"description\": \"Camisinha\",\n\t\"amount\": \"10\",\n\t\"price\": \"10.50\",\n\t\"type\": \"Pacote\",\n\t\"provider\": 1\n}"
		},
		{
			"id": "fb90d9cb-f71b-1d61-3797-f0e4d7d55677",
			"headers": "",
			"headerData": [],
			"url": "localhost:8080/product/2",
			"queryParams": [],
			"pathVariables": {},
			"pathVariableData": [],
			"preRequestScript": null,
			"method": "GET",
			"collectionId": "d78d8fe9-8754-a0ff-700a-a4583491246c",
			"data": null,
			"dataMode": "params",
			"name": "GetById",
			"description": "",
			"descriptionFormat": "html",
			"time": 1535587819300,
			"version": 2,
			"responses": [],
			"tests": null,
			"currentHelper": "normal",
			"helperAttributes": {}
		}
	]
}